digitalhub_runtime_dbt/__init__.py
digitalhub_runtime_dbt/entities/__init__.py
digitalhub_runtime_dbt/entities/_base/__init__.py
digitalhub_runtime_dbt/entities/_base/runtime_entity/__init__.py
digitalhub_runtime_dbt/entities/_base/runtime_entity/builder.py
digitalhub_runtime_dbt/entities/_commons/__init__.py
digitalhub_runtime_dbt/entities/_commons/enums.py
digitalhub_runtime_dbt/entities/function/__init__.py
digitalhub_runtime_dbt/entities/function/dbt/__init__.py
digitalhub_runtime_dbt/entities/function/dbt/builder.py
digitalhub_runtime_dbt/entities/function/dbt/entity.py
digitalhub_runtime_dbt/entities/function/dbt/models.py
digitalhub_runtime_dbt/entities/function/dbt/spec.py
digitalhub_runtime_dbt/entities/function/dbt/status.py
digitalhub_runtime_dbt/entities/function/dbt/utils.py
digitalhub_runtime_dbt/entities/run/__init__.py
digitalhub_runtime_dbt/entities/run/transform/__init__.py
digitalhub_runtime_dbt/entities/run/transform/builder.py
digitalhub_runtime_dbt/entities/run/transform/entity.py
digitalhub_runtime_dbt/entities/run/transform/spec.py
digitalhub_runtime_dbt/entities/run/transform/status.py
digitalhub_runtime_dbt/entities/run/transform/utils.py
digitalhub_runtime_dbt/entities/task/__init__.py
digitalhub_runtime_dbt/entities/task/transform/__init__.py
digitalhub_runtime_dbt/entities/task/transform/builder.py
digitalhub_runtime_dbt/entities/task/transform/entity.py
digitalhub_runtime_dbt/entities/task/transform/spec.py
digitalhub_runtime_dbt/entities/task/transform/status.py
digitalhub_runtime_dbt/runtimes/__init__.py
digitalhub_runtime_dbt/runtimes/builder.py
digitalhub_runtime_dbt/runtimes/runtime.py
digitalhub_runtime_dbt/utils/__init__.py
digitalhub_runtime_dbt/utils/configuration.py
digitalhub_runtime_dbt/utils/functions.py
digitalhub_runtime_dbt/utils/inputs.py
digitalhub_runtime_dbt/utils/outputs.py
digitalhub_runtime_dbt-0.14.0.dist-info/METADATA
digitalhub_runtime_dbt-0.14.0.dist-info/WHEEL
digitalhub_runtime_dbt-0.14.0.dist-info/licenses/AUTHORS
digitalhub_runtime_dbt-0.14.0.dist-info/licenses/LICENSE
digitalhub_runtime_dbt-0.14.0.dist-info/RECORD
